{
  "id": "b0e0ab02-daba-4bf2-a223-d4cee3af2d1f",
  "name": "button9",
  "type": "Button",
  "pageId": "b8b12223-955e-4668-bb36-b98e001c984f",
  "parent": "8be9939a-ca12-4ac2-b8e7-2866729ccc78",
  "properties": {
    "text": {
      "value": "Save changes"
    },
    "loadingState": {
      "value": "{{queries.updateProduct.isLoading}}",
      "fxActive": true
    },
    "visibility": {
      "value": "{{true}}"
    },
    "disabledState": {
      "value": "{{components.textinput2.value.length < 1 || components.numberinput5.value < 0 || components.numberinput6.value == 0 || components.dropdown5.value == undefined || components.dropdown6.value == undefined || components.textarea3.value == \"\"}}",
      "fxActive": true
    }
  },
  "general": {},
  "styles": {
    "backgroundColor": {
      "value": "#3e63ddff",
      "fxActive": false
    },
    "textColor": {
      "value": "#ffffffff",
      "fxActive": false
    },
    "loaderColor": {
      "value": "#ffffffff",
      "fxActive": false
    },
    "borderRadius": {
      "value": "{{6}}"
    },
    "borderColor": {
      "value": "#ffffff00",
      "fxActive": false
    },
    "boxShadow": {
      "value": "0px 0px 0px 0px #00000040"
    }
  },
  "generalStyles": {},
  "displayPreferences": {
    "showOnDesktop": {
      "value": "{{true}}"
    },
    "showOnMobile": {
      "value": "{{false}}"
    }
  },
  "validation": {},
  "layouts": [
    {
      "id": "8689f3c9-b279-4345-8710-a51abc8226df",
      "type": "desktop",
      "top": 420,
      "left": 33,
      "width": 8,
      "height": 40,
      "componentId": "b0e0ab02-daba-4bf2-a223-d4cee3af2d1f",
      "dimensionUnit": "count"
    }
  ]
}