{
  "id": "139903da-968f-49c4-9f28-8c46eeae9b88",
  "name": "text33",
  "type": "Text",
  "pageId": "8dd244fa-4665-431a-ab6b-7e49536a47ea",
  "parent": "05a0a0ca-e99f-4e57-873f-178fb7ea69ec-header",
  "properties": {
    "textFormat": {
      "value": "html"
    },
    "dynamicHeight": {
      "value": "{{false}}"
    },
    "text": {
      "value": "Container title"
    },
    "loadingState": {
      "value": "{{false}}"
    },
    "disabledState": {
      "value": "{{false}}"
    },
    "visibility": {
      "value": "{{true}}"
    },
    "fontWeight": {
      "value": "bold"
    },
    "textSize": {
      "value": 16
    },
    "textColor": {
      "value": "var(--cc-primary-text)"
    },
    "boxShadow": {
      "value": "0px 0px 0px 0px #00000090"
    },
    "verticalAlignment": {
      "value": "center"
    }
  },
  "general": {},
  "styles": {
    "backgroundColor": {
      "value": "#fff00000"
    },
    "textColor": {
      "value": "var(--cc-primary-text)"
    },
    "textSize": {
      "value": 16
    },
    "textAlign": {
      "value": "left"
    },
    "fontWeight": {
      "value": "bold"
    },
    "decoration": {
      "value": "none"
    },
    "transformation": {
      "value": "none"
    },
    "fontStyle": {
      "value": "normal"
    },
    "lineHeight": {
      "value": "{{1.5}}"
    },
    "textIndent": {
      "value": "{{0}}"
    },
    "letterSpacing": {
      "value": "{{0}}"
    },
    "wordSpacing": {
      "value": "{{0}}"
    },
    "fontVariant": {
      "value": "normal"
    },
    "verticalAlignment": {
      "value": "center"
    },
    "padding": {
      "value": "default"
    },
    "boxShadow": {
      "value": "0px 0px 0px 0px #00000090"
    },
    "borderColor": {
      "value": "#ffffff00"
    },
    "borderRadius": {
      "value": "{{6}}"
    },
    "isScrollRequired": {
      "value": "enabled"
    },
    "textFormat": {
      "value": "html"
    },
    "dynamicHeight": {
      "value": "{{false}}"
    },
    "text": {
      "value": "Container title"
    },
    "loadingState": {
      "value": "{{false}}"
    }
  },
  "generalStyles": {},
  "displayPreferences": {
    "showOnDesktop": {
      "value": "{{true}}"
    },
    "showOnMobile": {
      "value": "{{false}}"
    }
  },
  "validation": {},
  "layouts": [
    {
      "id": "c14c75a2-d56c-47a8-90c2-28af5e87e36b",
      "type": "desktop",
      "top": 20,
      "left": 1,
      "width": null,
      "height": 40,
      "componentId": "139903da-968f-49c4-9f28-8c46eeae9b88",
      "dimensionUnit": "count"
    },
    {
      "id": "e8daaca2-534b-4ac4-93c3-827b73ada38f",
      "type": "mobile",
      "top": 20,
      "left": 1,
      "width": 20,
      "height": 40,
      "componentId": "139903da-968f-49c4-9f28-8c46eeae9b88",
      "dimensionUnit": "count"
    }
  ]
}