{
  "id": "6d0e7a53-5868-45fe-84d5-053fa873926b",
  "name": "text63",
  "type": "Text",
  "pageId": "fc607843-7e10-4df7-9207-f0b12b9e8edd",
  "parent": "25944a5c-50cd-4545-81a7-7a7c430b893b-header",
  "properties": {
    "textFormat": {
      "value": "html"
    },
    "dynamicHeight": {
      "value": "{{false}}"
    },
    "text": {
      "value": "Container title"
    },
    "loadingState": {
      "value": "{{false}}"
    },
    "disabledState": {
      "value": "{{false}}"
    },
    "visibility": {
      "value": "{{true}}"
    },
    "fontWeight": {
      "value": "bold"
    },
    "textSize": {
      "value": 16
    },
    "textColor": {
      "value": "var(--cc-primary-text)"
    },
    "boxShadow": {
      "value": "0px 0px 0px 0px #00000090"
    },
    "verticalAlignment": {
      "value": "center"
    }
  },
  "general": {},
  "styles": {
    "backgroundColor": {
      "value": "#fff00000"
    },
    "textColor": {
      "value": "var(--cc-primary-text)"
    },
    "textSize": {
      "value": 16
    },
    "textAlign": {
      "value": "left"
    },
    "fontWeight": {
      "value": "bold"
    },
    "decoration": {
      "value": "none"
    },
    "transformation": {
      "value": "none"
    },
    "fontStyle": {
      "value": "normal"
    },
    "lineHeight": {
      "value": "{{1.5}}"
    },
    "textIndent": {
      "value": "{{0}}"
    },
    "letterSpacing": {
      "value": "{{0}}"
    },
    "wordSpacing": {
      "value": "{{0}}"
    },
    "fontVariant": {
      "value": "normal"
    },
    "verticalAlignment": {
      "value": "center"
    },
    "padding": {
      "value": "default"
    },
    "boxShadow": {
      "value": "0px 0px 0px 0px #00000090"
    },
    "borderColor": {
      "value": "#ffffff00"
    },
    "borderRadius": {
      "value": "{{6}}"
    },
    "isScrollRequired": {
      "value": "enabled"
    },
    "textFormat": {
      "value": "html"
    },
    "dynamicHeight": {
      "value": "{{false}}"
    },
    "text": {
      "value": "Container title"
    },
    "loadingState": {
      "value": "{{false}}"
    }
  },
  "generalStyles": {},
  "displayPreferences": {
    "showOnDesktop": {
      "value": "{{true}}"
    },
    "showOnMobile": {
      "value": "{{false}}"
    }
  },
  "validation": {},
  "layouts": [
    {
      "id": "abcbfd17-d700-453e-9441-82972f191ec5",
      "type": "desktop",
      "top": 20,
      "left": 1,
      "width": null,
      "height": 40,
      "componentId": "6d0e7a53-5868-45fe-84d5-053fa873926b",
      "dimensionUnit": "count"
    },
    {
      "id": "759c3dba-c24d-4cd6-84ab-73157f3fa8d9",
      "type": "mobile",
      "top": 20,
      "left": 1,
      "width": 20,
      "height": 40,
      "componentId": "6d0e7a53-5868-45fe-84d5-053fa873926b",
      "dimensionUnit": "count"
    }
  ]
}