{
  "id": "edc084e7-d8f5-441b-a2cf-e2efbe08af02",
  "name": "textinput40",
  "type": "TextInput",
  "pageId": "fc607843-7e10-4df7-9207-f0b12b9e8edd",
  "parent": "63cd9c4f-6b4f-424c-87de-95f12d815513",
  "properties": {
    "value": {
      "value": ""
    },
    "label": {
      "value": "CTA link"
    },
    "placeholder": {
      "value": "Enter your input"
    },
    "visibility": {
      "value": "{{true}}"
    },
    "disabledState": {
      "value": "{{false}}"
    },
    "loadingState": {
      "value": "{{false}}"
    },
    "tooltip": {
      "value": ""
    }
  },
  "general": {},
  "styles": {
    "textColor": {
      "value": "var(--cc-primary-text)"
    },
    "borderColor": {
      "value": "var(--cc-default-border)"
    },
    "accentColor": {
      "value": "var(--cc-primary-brand)"
    },
    "errTextColor": {
      "value": "var(--cc-error-systemStatus)"
    },
    "borderRadius": {
      "value": "{{6}}"
    },
    "backgroundColor": {
      "value": "var(--cc-surface1-surface)"
    },
    "iconColor": {
      "value": "var(--cc-default-icon)"
    },
    "direction": {
      "value": "left"
    },
    "width": {
      "value": "{{33}}"
    },
    "alignment": {
      "value": "top"
    },
    "color": {
      "value": "var(--cc-primary-text)"
    },
    "auto": {
      "value": "{{true}}"
    },
    "padding": {
      "value": "default"
    },
    "boxShadow": {
      "value": "0px 0px 0px 0px #00000040"
    },
    "icon": {
      "value": "IconHome2"
    },
    "iconVisibility": {
      "value": false
    },
    "widthType": {
      "value": "ofComponent"
    }
  },
  "generalStyles": {},
  "displayPreferences": {
    "showOnDesktop": {
      "value": "{{true}}"
    },
    "showOnMobile": {
      "value": "{{false}}"
    }
  },
  "validation": {
    "mandatory": {
      "value": "{{false}}"
    },
    "regex": {
      "value": ""
    },
    "minLength": {
      "value": ""
    },
    "maxLength": {
      "value": ""
    },
    "customRule": {
      "value": ""
    }
  },
  "layouts": [
    {
      "id": "f3c84de5-1191-4ab2-829a-3be26d3e6bbd",
      "type": "desktop",
      "top": 220,
      "left": 1,
      "width": 42,
      "height": 40,
      "componentId": "edc084e7-d8f5-441b-a2cf-e2efbe08af02",
      "dimensionUnit": "count"
    },
    {
      "id": "d71d367f-3a2d-4e95-81fa-76dddedd7be0",
      "type": "mobile",
      "top": 10,
      "left": 0,
      "width": 43,
      "height": 40,
      "componentId": "edc084e7-d8f5-441b-a2cf-e2efbe08af02",
      "dimensionUnit": "count"
    }
  ]
}