{
  "id": "f64406da-9bea-4cbe-87ee-a9ef06910146",
  "name": "textinput90",
  "type": "TextInput",
  "pageId": "fc607843-7e10-4df7-9207-f0b12b9e8edd",
  "parent": "7a99bd2b-932f-49bf-9aa5-b4526f76f409",
  "properties": {
    "value": {
      "value": ""
    },
    "label": {
      "value": "Description"
    },
    "placeholder": {
      "value": "Enter your input"
    },
    "visibility": {
      "value": "{{true}}"
    },
    "disabledState": {
      "value": "{{false}}"
    },
    "loadingState": {
      "value": "{{false}}"
    },
    "tooltip": {
      "value": ""
    }
  },
  "general": {},
  "styles": {
    "textColor": {
      "value": "var(--cc-primary-text)"
    },
    "borderColor": {
      "value": "var(--cc-default-border)"
    },
    "accentColor": {
      "value": "var(--cc-primary-brand)"
    },
    "errTextColor": {
      "value": "var(--cc-error-systemStatus)"
    },
    "borderRadius": {
      "value": "{{6}}"
    },
    "backgroundColor": {
      "value": "var(--cc-surface1-surface)"
    },
    "iconColor": {
      "value": "var(--cc-default-icon)"
    },
    "direction": {
      "value": "left"
    },
    "width": {
      "value": "{{33}}"
    },
    "alignment": {
      "value": "top"
    },
    "color": {
      "value": "var(--cc-primary-text)"
    },
    "auto": {
      "value": "{{true}}"
    },
    "padding": {
      "value": "default"
    },
    "boxShadow": {
      "value": "0px 0px 0px 0px #00000040"
    },
    "icon": {
      "value": "IconHome2"
    },
    "iconVisibility": {
      "value": false
    },
    "widthType": {
      "value": "ofComponent"
    }
  },
  "generalStyles": {},
  "displayPreferences": {
    "showOnDesktop": {
      "value": "{{true}}"
    },
    "showOnMobile": {
      "value": "{{false}}"
    }
  },
  "validation": {
    "mandatory": {
      "value": "{{false}}"
    },
    "regex": {
      "value": ""
    },
    "minLength": {
      "value": ""
    },
    "maxLength": {
      "value": ""
    },
    "customRule": {
      "value": ""
    }
  },
  "layouts": [
    {
      "id": "d61c22af-f4e4-4c8c-a2da-6f9ee5fe1fc0",
      "type": "desktop",
      "top": 80,
      "left": 1,
      "width": 42,
      "height": 40,
      "componentId": "f64406da-9bea-4cbe-87ee-a9ef06910146",
      "dimensionUnit": "count"
    },
    {
      "id": "4dfd9e14-4d37-4df8-918e-86c7b5a13d7d",
      "type": "mobile",
      "top": 10,
      "left": 0,
      "width": 43,
      "height": 40,
      "componentId": "f64406da-9bea-4cbe-87ee-a9ef06910146",
      "dimensionUnit": "count"
    }
  ]
}